COPYING
MANIFEST.in
README.rst
buildout.cfg
develop.cfg
requirements.txt
setup.py
version.txt
bob/__init__.py
bob.db.multipie.egg-info/PKG-INFO
bob.db.multipie.egg-info/SOURCES.txt
bob.db.multipie.egg-info/dependency_links.txt
bob.db.multipie.egg-info/entry_points.txt
bob.db.multipie.egg-info/not-zip-safe
bob.db.multipie.egg-info/requires.txt
bob.db.multipie.egg-info/top_level.txt
bob/db/__init__.py
bob/db/multipie/__init__.py
bob/db/multipie/create.py
bob/db/multipie/driver.py
bob/db/multipie/models.py
bob/db/multipie/query.py
bob/db/multipie/test.py
doc/conf.py
doc/guide.rst
doc/index.rst
doc/py_api.rst